pylotus_rpc/__init__.py
pylotus_rpc/http_json_rpc_connector.py
pylotus_rpc/lotus_client.py
pylotus_rpc/methods/__init__.py
pylotus_rpc/methods/chain.py
pylotus_rpc/methods/state.py
pylotus_rpc/types/__init__.py
pylotus_rpc/types/actor.py
pylotus_rpc/types/actor_state.py
pylotus_rpc/types/address.py
pylotus_rpc/types/block_header.py
pylotus_rpc/types/block_messages.py
pylotus_rpc/types/cid.py
pylotus_rpc/types/deadline.py
pylotus_rpc/types/deadline_info.py
pylotus_rpc/types/deal_proposal.py
pylotus_rpc/types/deal_state.py
pylotus_rpc/types/execution_trace.py
pylotus_rpc/types/gas_trace.py
pylotus_rpc/types/head_change.py
pylotus_rpc/types/invocation_result.py
pylotus_rpc/types/loc.py
pylotus_rpc/types/message.py
pylotus_rpc/types/message_gas_cost.py
pylotus_rpc/types/message_lookup.py
pylotus_rpc/types/message_receipt.py
pylotus_rpc/types/miner_info.py
pylotus_rpc/types/miner_partition.py
pylotus_rpc/types/miner_power.py
pylotus_rpc/types/sector.py
pylotus_rpc/types/sector_pre_commit_info.py
pylotus_rpc/types/signature.py
pylotus_rpc/types/signed_message.py
pylotus_rpc/types/state_compute_output.py
pylotus_rpc/types/tip_set.py
pylotus_rpc/types/wrapped_message.py
pylotus_rpc/util/sector_util.py
pylotus_rpc-0.5.dist-info/METADATA
pylotus_rpc-0.5.dist-info/WHEEL
pylotus_rpc-0.5.dist-info/licenses/LICENSE
pylotus_rpc-0.5.dist-info/RECORD
