Metadata-Version: 2.3
Name: pylotus-rpc
Version: 0.5
Summary: Python client for interacting with the Lotus JSON-RPC API.
Project-URL: Homepage, https://github.com/FilForge/pylotus-rpc
Project-URL: Issues, https://github.com/FilForge/pylotus-rpc/issues
Author: Jason Byteforgia
License:                              Apache License
Keywords: api,client,filecoin,json-rpc,lotus,python,rpc
Classifier: License :: OSI Approved :: MIT License
Classifier: Operating System :: OS Independent
Classifier: Programming Language :: Python :: 3
Requires-Python: >=3.8
Requires-Dist: requests
